linregmc/.bashlog
linregmc/__init__.py
linregmc/linregmc.py
linregmc-0.1.1.dist-info/LICENSE
linregmc-0.1.1.dist-info/METADATA
linregmc-0.1.1.dist-info/WHEEL
linregmc-0.1.1.dist-info/RECORD
