Metadata-Version: 2.3
Name: linregmc
Version: 0.1.1
Summary: Linear regression with Monte Carlo error analysis
License: MIT
Author: Pär Söderhjelm
Requires-Python: >=3.9,<4.0
Classifier: License :: OSI Approved :: MIT License
Classifier: Programming Language :: Python :: 3
Classifier: Programming Language :: Python :: 3.9
Classifier: Programming Language :: Python :: 3.10
Classifier: Programming Language :: Python :: 3.11
Classifier: Programming Language :: Python :: 3.12
Classifier: Programming Language :: Python :: 3.13
Requires-Dist: numpy (>=1.23,<3.0)
